mendive/__init__.py
mendive/algorithm.py
mendive/app.py
mendive/applogger.py
mendive/inverted.py
mendive/parser.py
mendive/test.py
mendive/utils.py
mendive-0.0.7.dist-info/licenses/LICENSE
mendive-0.0.7.dist-info/METADATA
mendive-0.0.7.dist-info/WHEEL
mendive-0.0.7.dist-info/entry_points.txt
mendive-0.0.7.dist-info/top_level.txt
mendive-0.0.7.dist-info/RECORD
